magic_space/README.md
magic_space/__init__.py
magic_space/main.py
magic_space/utils.py
magic_space/config/__init__.py
magic_space/tests/__init__.py
magic_space/tests/test_main.py
magicspace-1.0.1.dist-info/METADATA
magicspace-1.0.1.dist-info/WHEEL
magicspace-1.0.1.dist-info/entry_points.txt
magicspace-1.0.1.dist-info/top_level.txt
magicspace-1.0.1.dist-info/RECORD
