Metadata-Version: 2.1
Name: magicspace
Version: 1.0.1
Summary: Fast tool to open a set of apps (workspace) using a single command.
Home-page: https://github.com/lakshya7878/MagicSpace
Author: Lakshya Sharma
Author-email: lakshya7878@gmail.com
License: MIT License
Classifier: Programming Language :: Python :: 3.11
Classifier: License :: OSI Approved :: MIT License
Classifier: Operating System :: OS Independent
Requires-Python: >=3.6
